setup.py
test/__init__.py
test/test_add_promotion.py
test/test_add_promotion_api.py
test/test_add_to_cart.py
test/test_add_to_cart_api.py
test/test_billing_address.py
test/test_chargeback.py
test/test_chargeback_api.py
test/test_create_account.py
test/test_create_account_api.py
test/test_create_order.py
test/test_create_order_api.py
test/test_custom.py
test/test_custom_event_api.py
test/test_custom_info.py
test/test_error_response.py
test/test_event_response.py
test/test_item.py
test/test_item_status.py
test/test_item_status_api.py
test/test_link_session_to_user.py
test/test_link_session_to_user_api.py
test/test_login.py
test/test_login_api.py
test/test_logout.py
test/test_logout_api.py
test/test_order_status.py
test/test_order_status_api.py
test/test_payment_method.py
test/test_promotion.py
test/test_remove_from_cart.py
test/test_remove_from_cart_api.py
test/test_report_item.py
test/test_report_item_api.py
test/test_seller.py
test/test_send_message.py
test/test_send_message_api.py
test/test_shipping_address.py
test/test_submit_review.py
test/test_submit_review_api.py
test/test_tag.py
test/test_tag_api_api.py
test/test_transaction.py
test/test_transaction_api.py
test/test_un_tag.py
test/test_untag_api_api.py
test/test_update_account.py
test/test_update_account_api.py
test/test_update_order.py
test/test_update_order_api.py
thirdwatch_api/__init__.py
thirdwatch_api/api_client.py
thirdwatch_api/configuration.py
thirdwatch_api/rest.py
thirdwatch_api.egg-info/PKG-INFO
thirdwatch_api.egg-info/SOURCES.txt
thirdwatch_api.egg-info/dependency_links.txt
thirdwatch_api.egg-info/requires.txt
thirdwatch_api.egg-info/top_level.txt
thirdwatch_api/apis/__init__.py
thirdwatch_api/apis/add_promotion_api.py
thirdwatch_api/apis/add_to_cart_api.py
thirdwatch_api/apis/chargeback_api.py
thirdwatch_api/apis/create_account_api.py
thirdwatch_api/apis/create_order_api.py
thirdwatch_api/apis/custom_event_api.py
thirdwatch_api/apis/item_status_api.py
thirdwatch_api/apis/link_session_to_user_api.py
thirdwatch_api/apis/login_api.py
thirdwatch_api/apis/logout_api.py
thirdwatch_api/apis/order_status_api.py
thirdwatch_api/apis/remove_from_cart_api.py
