Metadata-Version: 1.0
Name: thirdwatch-api
Version: 0.0.3
Summary: Thirdwatch API
Home-page: https://github.com/thirdwatch/thirdwatch-python
Author: UNKNOWN
Author-email: shashank@thirdwatch.ai
License: UNKNOWN
Keywords: Swagger,Thirdwatch API
Platform: UNKNOWN
